st_speckmol/__init__.py
st_speckmol/utils.py
st_speckmol/version.py
st_speckmol-0.0.6.dist-info/LICENSE
st_speckmol-0.0.6.dist-info/METADATA
st_speckmol-0.0.6.dist-info/WHEEL
st_speckmol-0.0.6.dist-info/top_level.txt
st_speckmol-0.0.6.dist-info/RECORD
