Metadata-Version: 2.1
Name: st-speckmol
Version: 0.0.6
Summary: Streamlit component for for Speck molecule visualization.
Home-page: https://github.com/avrabyt/Specklit
Author: Avratanu Biswas
Author-email: avrab.yt@gmail.com
Requires-Python: >=3.6
License-File: LICENSE
Requires-Dist: streamlit (>=0.63)
Requires-Dist: ipyspeck (==0.6.1)
Requires-Dist: ipywidgets (==7.6.3)
